{"name":{"en":"Czech Republic","fr":"République tchèque","ar":"التشيك"},"code":"CZ","capital":"Prague","language":"Czech","dialling":{"calling_code":["420"],"national_prefix":null,"national_number_lengths":[9],"national_destination_code_lengths":[2],"international_prefix":"00"},"currency":{"name":"Czech Republic Koruna","code":"CZK"},"cities":{"PRAGUE-CZ":{"name":{"en":"Prague","ar":"","fr":""},"code":"PRAGUE-CZ","countryCode":"CZ"},"BRNO-CZ":{"name":{"en":"Brno","ar":"","fr":""},"code":"BRNO-CZ","countryCode":"CZ"},"OSTRAVA-CZ":{"name":{"en":"Ostrava","ar":"","fr":""},"code":"OSTRAVA-CZ","countryCode":"CZ"},"PLZEN-CZ":{"name":{"en":"Plzen","ar":"","fr":""},"code":"PLZEN-CZ","countryCode":"CZ"},"LIBEREC-CZ":{"name":{"en":"Liberec","ar":"","fr":""},"code":"LIBEREC-CZ","countryCode":"CZ"},"OLOMOUC-CZ":{"name":{"en":"Olomouc","ar":"","fr":""},"code":"OLOMOUC-CZ","countryCode":"CZ"},"CESKE-BUDEJOVICE-CZ":{"name":{"en":"Ceske Budejovice","ar":"","fr":""},"code":"CESKE-BUDEJOVICE-CZ","countryCode":"CZ"},"HRADEC-KRALOVE-CZ":{"name":{"en":"Hradec Kralove","ar":"","fr":""},"code":"HRADEC-KRALOVE-CZ","countryCode":"CZ"},"PARDUBICE-CZ":{"name":{"en":"Pardubice","ar":"","fr":""},"code":"PARDUBICE-CZ","countryCode":"CZ"},"USTI-NAD-LABEM-CZ":{"name":{"en":"Usti nad Labem","ar":"","fr":""},"code":"USTI-NAD-LABEM-CZ","countryCode":"CZ"},"ZLIN-CZ":{"name":{"en":"Zlin","ar":"","fr":""},"code":"ZLIN-CZ","countryCode":"CZ"},"HAVIROV-CZ":{"name":{"en":"Havirov","ar":"","fr":""},"code":"HAVIROV-CZ","countryCode":"CZ"},"KLADNO-CZ":{"name":{"en":"Kladno","ar":"","fr":""},"code":"KLADNO-CZ","countryCode":"CZ"},"MOST-CZ":{"name":{"en":"Most","ar":"","fr":""},"code":"MOST-CZ","countryCode":"CZ"},"OPAVA-CZ":{"name":{"en":"Opava","ar":"","fr":""},"code":"OPAVA-CZ","countryCode":"CZ"},"FRYDEK-MISTEK-CZ":{"name":{"en":"Frydek-Mistek","ar":"","fr":""},"code":"FRYDEK-MISTEK-CZ","countryCode":"CZ"},"JIHLAVA-CZ":{"name":{"en":"Jihlava","ar":"","fr":""},"code":"JIHLAVA-CZ","countryCode":"CZ"},"TEPLICE-CZ":{"name":{"en":"Teplice","ar":"","fr":""},"code":"TEPLICE-CZ","countryCode":"CZ"},"KARVINA-CZ":{"name":{"en":"Karvina","ar":"","fr":""},"code":"KARVINA-CZ","countryCode":"CZ"},"KARLOVY-VARY-CZ":{"name":{"en":"Karlovy Vary","ar":"","fr":""},"code":"KARLOVY-VARY-CZ","countryCode":"CZ"},"DECIN-CZ":{"name":{"en":"Decin","ar":"","fr":""},"code":"DECIN-CZ","countryCode":"CZ"},"CHOMUTOV-CZ":{"name":{"en":"Chomutov","ar":"","fr":""},"code":"CHOMUTOV-CZ","countryCode":"CZ"},"JABLONEC-NAD-NISOU-CZ":{"name":{"en":"Jablonec nad Nisou","ar":"","fr":""},"code":"JABLONEC-NAD-NISOU-CZ","countryCode":"CZ"},"MLADA-BOLESLAV-CZ":{"name":{"en":"Mlada Boleslav","ar":"","fr":""},"code":"MLADA-BOLESLAV-CZ","countryCode":"CZ"},"PROSTEJOV-CZ":{"name":{"en":"Prostejov","ar":"","fr":""},"code":"PROSTEJOV-CZ","countryCode":"CZ"},"PREROV-CZ":{"name":{"en":"Prerov","ar":"","fr":""},"code":"PREROV-CZ","countryCode":"CZ"},"CESKA-LIPA-CZ":{"name":{"en":"Ceska Lipa","ar":"","fr":""},"code":"CESKA-LIPA-CZ","countryCode":"CZ"},"TREBIC-CZ":{"name":{"en":"Trebic","ar":"","fr":""},"code":"TREBIC-CZ","countryCode":"CZ"},"TRINEC-CZ":{"name":{"en":"Trinec","ar":"","fr":""},"code":"TRINEC-CZ","countryCode":"CZ"},"TABOR-CZ":{"name":{"en":"Tabor","ar":"","fr":""},"code":"TABOR-CZ","countryCode":"CZ"},"ZNOJMO-CZ":{"name":{"en":"Znojmo","ar":"","fr":""},"code":"ZNOJMO-CZ","countryCode":"CZ"},"KOLIN-CZ":{"name":{"en":"Kolin","ar":"","fr":""},"code":"KOLIN-CZ","countryCode":"CZ"},"PRIBRAM-CZ":{"name":{"en":"Pribram","ar":"","fr":""},"code":"PRIBRAM-CZ","countryCode":"CZ"},"CHEB-CZ":{"name":{"en":"Cheb","ar":"","fr":""},"code":"CHEB-CZ","countryCode":"CZ"},"PISEK-CZ":{"name":{"en":"Pisek","ar":"","fr":""},"code":"PISEK-CZ","countryCode":"CZ"},"TRUTNOV-CZ":{"name":{"en":"Trutnov","ar":"","fr":""},"code":"TRUTNOV-CZ","countryCode":"CZ"},"KROMERIZ-CZ":{"name":{"en":"Kromeriz","ar":"","fr":""},"code":"KROMERIZ-CZ","countryCode":"CZ"},"ORLOVA-CZ":{"name":{"en":"Orlova","ar":"","fr":""},"code":"ORLOVA-CZ","countryCode":"CZ"},"LISEN-CZ":{"name":{"en":"Lisen","ar":"","fr":""},"code":"LISEN-CZ","countryCode":"CZ"},"BREVNOV-CZ":{"name":{"en":"Brevnov","ar":"","fr":""},"code":"BREVNOV-CZ","countryCode":"CZ"},"VSETIN-CZ":{"name":{"en":"Vsetin","ar":"","fr":""},"code":"VSETIN-CZ","countryCode":"CZ"},"SUMPERK-CZ":{"name":{"en":"Sumperk","ar":"","fr":""},"code":"SUMPERK-CZ","countryCode":"CZ"},"UHERSKE-HRADISTE-CZ":{"name":{"en":"Uherske Hradiste","ar":"","fr":""},"code":"UHERSKE-HRADISTE-CZ","countryCode":"CZ"},"BYSTRC-CZ":{"name":{"en":"Bystrc","ar":"","fr":""},"code":"BYSTRC-CZ","countryCode":"CZ"},"BRECLAV-CZ":{"name":{"en":"Breclav","ar":"","fr":""},"code":"BRECLAV-CZ","countryCode":"CZ"},"HODONIN-CZ":{"name":{"en":"Hodonin","ar":"","fr":""},"code":"HODONIN-CZ","countryCode":"CZ"},"CESKY-TESIN-CZ":{"name":{"en":"Cesky Tesin","ar":"","fr":""},"code":"CESKY-TESIN-CZ","countryCode":"CZ"},"CHRUDIM-CZ":{"name":{"en":"Chrudim","ar":"","fr":""},"code":"CHRUDIM-CZ","countryCode":"CZ"},"HAVLICKUV-BROD-CZ":{"name":{"en":"Havlickuv Brod","ar":"","fr":""},"code":"HAVLICKUV-BROD-CZ","countryCode":"CZ"},"LITOMERICE-CZ":{"name":{"en":"Litomerice","ar":"","fr":""},"code":"LITOMERICE-CZ","countryCode":"CZ"},"NOVY-JICIN-CZ":{"name":{"en":"Novy Jicin","ar":"","fr":""},"code":"NOVY-JICIN-CZ","countryCode":"CZ"},"KRNOV-CZ":{"name":{"en":"Krnov","ar":"","fr":""},"code":"KRNOV-CZ","countryCode":"CZ"},"LITVINOV-CZ":{"name":{"en":"Litvinov","ar":"","fr":""},"code":"LITVINOV-CZ","countryCode":"CZ"},"VALASSKE-MEZIRICI-CZ":{"name":{"en":"Valasske Mezirici","ar":"","fr":""},"code":"VALASSKE-MEZIRICI-CZ","countryCode":"CZ"},"STRAKONICE-CZ":{"name":{"en":"Strakonice","ar":"","fr":""},"code":"STRAKONICE-CZ","countryCode":"CZ"},"KLATOVY-CZ":{"name":{"en":"Klatovy","ar":"","fr":""},"code":"KLATOVY-CZ","countryCode":"CZ"},"SOKOLOV-CZ":{"name":{"en":"Sokolov","ar":"","fr":""},"code":"SOKOLOV-CZ","countryCode":"CZ"},"KOPRIVNICE-CZ":{"name":{"en":"Koprivnice","ar":"","fr":""},"code":"KOPRIVNICE-CZ","countryCode":"CZ"},"KUTNA-HORA-CZ":{"name":{"en":"Kutna Hora","ar":"","fr":""},"code":"KUTNA-HORA-CZ","countryCode":"CZ"},"JINDRICHUV-HRADEC-CZ":{"name":{"en":"Jindrichuv Hradec","ar":"","fr":""},"code":"JINDRICHUV-HRADEC-CZ","countryCode":"CZ"},"BEROUN-CZ":{"name":{"en":"Beroun","ar":"","fr":""},"code":"BEROUN-CZ","countryCode":"CZ"},"BOHUMIN-CZ":{"name":{"en":"Bohumin","ar":"","fr":""},"code":"BOHUMIN-CZ","countryCode":"CZ"},"ZD'AR-NAD-SAZAVOU-CZ":{"name":{"en":"Zd'ar nad Sazavou","ar":"","fr":""},"code":"ZD'AR-NAD-SAZAVOU-CZ","countryCode":"CZ"},"VYSKOV-CZ":{"name":{"en":"Vyskov","ar":"","fr":""},"code":"VYSKOV-CZ","countryCode":"CZ"},"MELNIK-CZ":{"name":{"en":"Melnik","ar":"","fr":""},"code":"MELNIK-CZ","countryCode":"CZ"},"BLANSKO-CZ":{"name":{"en":"Blansko","ar":"","fr":""},"code":"BLANSKO-CZ","countryCode":"CZ"},"NACHOD-CZ":{"name":{"en":"Nachod","ar":"","fr":""},"code":"NACHOD-CZ","countryCode":"CZ"},"BRANDYS-NAD-LABEM-STARA-BOLESLAV-CZ":{"name":{"en":"Brandys nad Labem-Stara Boleslav","ar":"","fr":""},"code":"BRANDYS-NAD-LABEM-STARA-BOLESLAV-CZ","countryCode":"CZ"},"JIRKOV-CZ":{"name":{"en":"Jirkov","ar":"","fr":""},"code":"JIRKOV-CZ","countryCode":"CZ"},"ZATEC-CZ":{"name":{"en":"Zatec","ar":"","fr":""},"code":"ZATEC-CZ","countryCode":"CZ"},"KRALUPY-NAD-VLTAVOU-CZ":{"name":{"en":"Kralupy nad Vltavou","ar":"","fr":""},"code":"KRALUPY-NAD-VLTAVOU-CZ","countryCode":"CZ"},"KADAN-CZ":{"name":{"en":"Kadan","ar":"","fr":""},"code":"KADAN-CZ","countryCode":"CZ"},"LOUNY-CZ":{"name":{"en":"Louny","ar":"","fr":""},"code":"LOUNY-CZ","countryCode":"CZ"},"HRANICE-CZ":{"name":{"en":"Hranice","ar":"","fr":""},"code":"HRANICE-CZ","countryCode":"CZ"},"OTROKOVICE-CZ":{"name":{"en":"Otrokovice","ar":"","fr":""},"code":"OTROKOVICE-CZ","countryCode":"CZ"},"BENESOV-CZ":{"name":{"en":"Benesov","ar":"","fr":""},"code":"BENESOV-CZ","countryCode":"CZ"},"RICANY-CZ":{"name":{"en":"Ricany","ar":"","fr":""},"code":"RICANY-CZ","countryCode":"CZ"},"SLANY-CZ":{"name":{"en":"Slany","ar":"","fr":""},"code":"SLANY-CZ","countryCode":"CZ"},"PELHRIMOV-CZ":{"name":{"en":"Pelhrimov","ar":"","fr":""},"code":"PELHRIMOV-CZ","countryCode":"CZ"},"UHERSKY-BROD-CZ":{"name":{"en":"Uhersky Brod","ar":"","fr":""},"code":"UHERSKY-BROD-CZ","countryCode":"CZ"},"NERATOVICE-CZ":{"name":{"en":"Neratovice","ar":"","fr":""},"code":"NERATOVICE-CZ","countryCode":"CZ"},"JICIN-CZ":{"name":{"en":"Jicin","ar":"","fr":""},"code":"JICIN-CZ","countryCode":"CZ"},"ROZNOV-POD-RADHOSTEM-CZ":{"name":{"en":"Roznov pod Radhostem","ar":"","fr":""},"code":"ROZNOV-POD-RADHOSTEM-CZ","countryCode":"CZ"},"SVITAVY-CZ":{"name":{"en":"Svitavy","ar":"","fr":""},"code":"SVITAVY-CZ","countryCode":"CZ"},"OSTROV-CZ":{"name":{"en":"Ostrov","ar":"","fr":""},"code":"OSTROV-CZ","countryCode":"CZ"},"RAKOVNIK-CZ":{"name":{"en":"Rakovnik","ar":"","fr":""},"code":"RAKOVNIK-CZ","countryCode":"CZ"},"NYMBURK-CZ":{"name":{"en":"Nymburk","ar":"","fr":""},"code":"NYMBURK-CZ","countryCode":"CZ"},"BRUNTAL-CZ":{"name":{"en":"Bruntal","ar":"","fr":""},"code":"BRUNTAL-CZ","countryCode":"CZ"},"DVUR-KRALOVE-NAD-LABEM-CZ":{"name":{"en":"Dvur Kralove nad Labem","ar":"","fr":""},"code":"DVUR-KRALOVE-NAD-LABEM-CZ","countryCode":"CZ"},"CESKA-TREBOVA-CZ":{"name":{"en":"Ceska Trebova","ar":"","fr":""},"code":"CESKA-TREBOVA-CZ","countryCode":"CZ"},"PODEBRADY-CZ":{"name":{"en":"Podebrady","ar":"","fr":""},"code":"PODEBRADY-CZ","countryCode":"CZ"},"VARNSDORF-CZ":{"name":{"en":"Varnsdorf","ar":"","fr":""},"code":"VARNSDORF-CZ","countryCode":"CZ"},"BILINA-CZ":{"name":{"en":"Bilina","ar":"","fr":""},"code":"BILINA-CZ","countryCode":"CZ"},"TURNOV-CZ":{"name":{"en":"Turnov","ar":"","fr":""},"code":"TURNOV-CZ","countryCode":"CZ"},"KLASTEREC-NAD-OHRI-CZ":{"name":{"en":"Klasterec nad Ohri","ar":"","fr":""},"code":"KLASTEREC-NAD-OHRI-CZ","countryCode":"CZ"},"ROKYCANY-CZ":{"name":{"en":"Rokycany","ar":"","fr":""},"code":"ROKYCANY-CZ","countryCode":"CZ"},"USTI-NAD-ORLICI-CZ":{"name":{"en":"Usti nad Orlici","ar":"","fr":""},"code":"USTI-NAD-ORLICI-CZ","countryCode":"CZ"},"TACHOV-CZ":{"name":{"en":"Tachov","ar":"","fr":""},"code":"TACHOV-CZ","countryCode":"CZ"},"MARIANSKE-LAZNE-CZ":{"name":{"en":"Marianske Lazne","ar":"","fr":""},"code":"MARIANSKE-LAZNE-CZ","countryCode":"CZ"},"MILOVICE-CZ":{"name":{"en":"Milovice","ar":"","fr":""},"code":"MILOVICE-CZ","countryCode":"CZ"},"HLUCIN-CZ":{"name":{"en":"Hlucin","ar":"","fr":""},"code":"HLUCIN-CZ","countryCode":"CZ"},"ZABREH-CZ":{"name":{"en":"Zabreh","ar":"","fr":""},"code":"ZABREH-CZ","countryCode":"CZ"},"STERNBERK-CZ":{"name":{"en":"Sternberk","ar":"","fr":""},"code":"STERNBERK-CZ","countryCode":"CZ"},"CESKY-KRUMLOV-CZ":{"name":{"en":"Cesky Krumlov","ar":"","fr":""},"code":"CESKY-KRUMLOV-CZ","countryCode":"CZ"},"AS-CZ":{"name":{"en":"As","ar":"","fr":""},"code":"AS-CZ","countryCode":"CZ"},"ROUDNICE-NAD-LABEM-CZ":{"name":{"en":"Roudnice nad Labem","ar":"","fr":""},"code":"ROUDNICE-NAD-LABEM-CZ","countryCode":"CZ"},"CHODOV-CZ":{"name":{"en":"Chodov","ar":"","fr":""},"code":"CHODOV-CZ","countryCode":"CZ"},"KRUPKA-CZ":{"name":{"en":"Krupka","ar":"","fr":""},"code":"KRUPKA-CZ","countryCode":"CZ"},"JAROMER-CZ":{"name":{"en":"Jaromer","ar":"","fr":""},"code":"JAROMER-CZ","countryCode":"CZ"},"CELAKOVICE-CZ":{"name":{"en":"Celakovice","ar":"","fr":""},"code":"CELAKOVICE-CZ","countryCode":"CZ"},"VYSOKE-MYTO-CZ":{"name":{"en":"Vysoke Myto","ar":"","fr":""},"code":"VYSOKE-MYTO-CZ","countryCode":"CZ"},"VRCHLABI-CZ":{"name":{"en":"Vrchlabi","ar":"","fr":""},"code":"VRCHLABI-CZ","countryCode":"CZ"},"BOSKOVICE-CZ":{"name":{"en":"Boskovice","ar":"","fr":""},"code":"BOSKOVICE-CZ","countryCode":"CZ"},"HOLESOV-CZ":{"name":{"en":"Holesov","ar":"","fr":""},"code":"HOLESOV-CZ","countryCode":"CZ"},"VELKE-MEZIRICI-CZ":{"name":{"en":"Velke Mezirici","ar":"","fr":""},"code":"VELKE-MEZIRICI-CZ","countryCode":"CZ"},"NOVY-BOR-CZ":{"name":{"en":"Novy Bor","ar":"","fr":""},"code":"NOVY-BOR-CZ","countryCode":"CZ"},"VLASIM-CZ":{"name":{"en":"Vlasim","ar":"","fr":""},"code":"VLASIM-CZ","countryCode":"CZ"},"HUMPOLEC-CZ":{"name":{"en":"Humpolec","ar":"","fr":""},"code":"HUMPOLEC-CZ","countryCode":"CZ"},"KURIM-CZ":{"name":{"en":"Kurim","ar":"","fr":""},"code":"KURIM-CZ","countryCode":"CZ"},"PRACHATICE-CZ":{"name":{"en":"Prachatice","ar":"","fr":""},"code":"PRACHATICE-CZ","countryCode":"CZ"},"RYCHNOV-NAD-KNEZNOU-CZ":{"name":{"en":"Rychnov nad Kneznou","ar":"","fr":""},"code":"RYCHNOV-NAD-KNEZNOU-CZ","countryCode":"CZ"},"UNICOV-CZ":{"name":{"en":"Unicov","ar":"","fr":""},"code":"UNICOV-CZ","countryCode":"CZ"},"DOMAZLICE-CZ":{"name":{"en":"Domazlice","ar":"","fr":""},"code":"DOMAZLICE-CZ","countryCode":"CZ"},"RUMBURK-CZ":{"name":{"en":"Rumburk","ar":"","fr":""},"code":"RUMBURK-CZ","countryCode":"CZ"},"KYJOV-CZ":{"name":{"en":"Kyjov","ar":"","fr":""},"code":"KYJOV-CZ","countryCode":"CZ"},"SUSICE-CZ":{"name":{"en":"Susice","ar":"","fr":""},"code":"SUSICE-CZ","countryCode":"CZ"},"FRENSTAT-POD-RADHOSTEM-CZ":{"name":{"en":"Frenstat pod Radhostem","ar":"","fr":""},"code":"FRENSTAT-POD-RADHOSTEM-CZ","countryCode":"CZ"},"JESENIK-CZ":{"name":{"en":"Jesenik","ar":"","fr":""},"code":"JESENIK-CZ","countryCode":"CZ"},"VESELI-NAD-MORAVOU-CZ":{"name":{"en":"Veseli nad Moravou","ar":"","fr":""},"code":"VESELI-NAD-MORAVOU-CZ","countryCode":"CZ"},"CASLAV-CZ":{"name":{"en":"Caslav","ar":"","fr":""},"code":"CASLAV-CZ","countryCode":"CZ"},"LITOMYSL-CZ":{"name":{"en":"Litomysl","ar":"","fr":""},"code":"LITOMYSL-CZ","countryCode":"CZ"},"KRALUV-DVUR-CZ":{"name":{"en":"Kraluv Dvur","ar":"","fr":""},"code":"KRALUV-DVUR-CZ","countryCode":"CZ"},"JESENICE-CZ":{"name":{"en":"Jesenice","ar":"","fr":""},"code":"JESENICE-CZ","countryCode":"CZ"},"LYSA-NAD-LABEM-CZ":{"name":{"en":"Lysa nad Labem","ar":"","fr":""},"code":"LYSA-NAD-LABEM-CZ","countryCode":"CZ"},"PRELOUC-CZ":{"name":{"en":"Prelouc","ar":"","fr":""},"code":"PRELOUC-CZ","countryCode":"CZ"},"NOVE-MESTO-NA-MORAVE-CZ":{"name":{"en":"Nove Mesto na Morave","ar":"","fr":""},"code":"NOVE-MESTO-NA-MORAVE-CZ","countryCode":"CZ"},"FRYDLANT-NAD-OSTRAVICI-CZ":{"name":{"en":"Frydlant nad Ostravici","ar":"","fr":""},"code":"FRYDLANT-NAD-OSTRAVICI-CZ","countryCode":"CZ"},"IVANCICE-CZ":{"name":{"en":"Ivancice","ar":"","fr":""},"code":"IVANCICE-CZ","countryCode":"CZ"},"LITOVEL-CZ":{"name":{"en":"Litovel","ar":"","fr":""},"code":"LITOVEL-CZ","countryCode":"CZ"},"LANSKROUN-CZ":{"name":{"en":"Lanskroun","ar":"","fr":""},"code":"LANSKROUN-CZ","countryCode":"CZ"},"MORAVSKA-TREBOVA-CZ":{"name":{"en":"Moravska Trebova","ar":"","fr":""},"code":"MORAVSKA-TREBOVA-CZ","countryCode":"CZ"},"HLINSKO-CZ":{"name":{"en":"Hlinsko","ar":"","fr":""},"code":"HLINSKO-CZ","countryCode":"CZ"},"MOHELNICE-CZ":{"name":{"en":"Mohelnice","ar":"","fr":""},"code":"MOHELNICE-CZ","countryCode":"CZ"},"NOVE-MESTO-NAD-METUJI-CZ":{"name":{"en":"Nove Mesto nad Metuji","ar":"","fr":""},"code":"NOVE-MESTO-NAD-METUJI-CZ","countryCode":"CZ"},"STUDENKA-CZ":{"name":{"en":"Studenka","ar":"","fr":""},"code":"STUDENKA-CZ","countryCode":"CZ"},"TISNOV-CZ":{"name":{"en":"Tisnov","ar":"","fr":""},"code":"TISNOV-CZ","countryCode":"CZ"},"HOSTIVICE-CZ":{"name":{"en":"Hostivice","ar":"","fr":""},"code":"HOSTIVICE-CZ","countryCode":"CZ"},"CHOTEBOR-CZ":{"name":{"en":"Chotebor","ar":"","fr":""},"code":"CHOTEBOR-CZ","countryCode":"CZ"},"NOVA-PAKA-CZ":{"name":{"en":"Nova Paka","ar":"","fr":""},"code":"NOVA-PAKA-CZ","countryCode":"CZ"},"ROZTOKY-CZ":{"name":{"en":"Roztoky","ar":"","fr":""},"code":"ROZTOKY-CZ","countryCode":"CZ"},"MNICHOVO-HRADISTE-CZ":{"name":{"en":"Mnichovo Hradiste","ar":"","fr":""},"code":"MNICHOVO-HRADISTE-CZ","countryCode":"CZ"},"POLICKA-CZ":{"name":{"en":"Policka","ar":"","fr":""},"code":"POLICKA-CZ","countryCode":"CZ"},"DOBRIS-CZ":{"name":{"en":"Dobris","ar":"","fr":""},"code":"DOBRIS-CZ","countryCode":"CZ"},"LOVOSICE-CZ":{"name":{"en":"Lovosice","ar":"","fr":""},"code":"LOVOSICE-CZ","countryCode":"CZ"},"CHOCEN-CZ":{"name":{"en":"Chocen","ar":"","fr":""},"code":"CHOCEN-CZ","countryCode":"CZ"},"DUCHCOV-CZ":{"name":{"en":"Duchcov","ar":"","fr":""},"code":"DUCHCOV-CZ","countryCode":"CZ"},"STETI-CZ":{"name":{"en":"Steti","ar":"","fr":""},"code":"STETI-CZ","countryCode":"CZ"},"HORICE-CZ":{"name":{"en":"Horice","ar":"","fr":""},"code":"HORICE-CZ","countryCode":"CZ"}}}