{"name":{"en":"Hungary","fr":"Hongrie"},"code":"HU","capital":"Budapest","language":"Hungarian","dialling":{"calling_code":["36"],"national_prefix":"06","national_number_lengths":[8,9],"national_destination_code_lengths":[2],"international_prefix":"00"},"currency":{"name":"Hungarian Forint","code":"HUF"},"cities":{"BUDAPEST-HU":{"name":{"en":"Budapest","ar":"","fr":""},"code":"BUDAPEST-HU","countryCode":"HU"},"DEBRECEN-HU":{"name":{"en":"Debrecen","ar":"","fr":""},"code":"DEBRECEN-HU","countryCode":"HU"},"SZEKESFEHERVAR-HU":{"name":{"en":"Szekesfehervar","ar":"","fr":""},"code":"SZEKESFEHERVAR-HU","countryCode":"HU"},"PECS-HU":{"name":{"en":"Pecs","ar":"","fr":""},"code":"PECS-HU","countryCode":"HU"},"GYOR-HU":{"name":{"en":"Gyor","ar":"","fr":""},"code":"GYOR-HU","countryCode":"HU"},"SZEGED-HU":{"name":{"en":"Szeged","ar":"","fr":""},"code":"SZEGED-HU","countryCode":"HU"},"NYIREGYHAZA-HU":{"name":{"en":"Nyiregyhaza","ar":"","fr":""},"code":"NYIREGYHAZA-HU","countryCode":"HU"},"KECSKEMET-HU":{"name":{"en":"Kecskemet","ar":"","fr":""},"code":"KECSKEMET-HU","countryCode":"HU"},"SZOMBATHELY-HU":{"name":{"en":"Szombathely","ar":"","fr":""},"code":"SZOMBATHELY-HU","countryCode":"HU"},"MISKOLC-HU":{"name":{"en":"Miskolc","ar":"","fr":""},"code":"MISKOLC-HU","countryCode":"HU"},"VESZPREM-HU":{"name":{"en":"Veszprem","ar":"","fr":""},"code":"VESZPREM-HU","countryCode":"HU"},"KAPOSVAR-HU":{"name":{"en":"Kaposvar","ar":"","fr":""},"code":"KAPOSVAR-HU","countryCode":"HU"},"GODOLLO-HU":{"name":{"en":"Godollo","ar":"","fr":""},"code":"GODOLLO-HU","countryCode":"HU"},"SOPRON-HU":{"name":{"en":"Sopron","ar":"","fr":""},"code":"SOPRON-HU","countryCode":"HU"},"ERD-HU":{"name":{"en":"Erd","ar":"","fr":""},"code":"ERD-HU","countryCode":"HU"},"SZOLNOK-HU":{"name":{"en":"Szolnok","ar":"","fr":""},"code":"SZOLNOK-HU","countryCode":"HU"},"TATABANYA-HU":{"name":{"en":"Tatabanya","ar":"","fr":""},"code":"TATABANYA-HU","countryCode":"HU"},"ZALAEGERSZEG-HU":{"name":{"en":"Zalaegerszeg","ar":"","fr":""},"code":"ZALAEGERSZEG-HU","countryCode":"HU"},"BEKESCSABA-HU":{"name":{"en":"Bekescsaba","ar":"","fr":""},"code":"BEKESCSABA-HU","countryCode":"HU"},"EGER-HU":{"name":{"en":"Eger","ar":"","fr":""},"code":"EGER-HU","countryCode":"HU"},"NAGYKANIZSA-HU":{"name":{"en":"Nagykanizsa","ar":"","fr":""},"code":"NAGYKANIZSA-HU","countryCode":"HU"},"DUNAKESZI-HU":{"name":{"en":"Dunakeszi","ar":"","fr":""},"code":"DUNAKESZI-HU","countryCode":"HU"},"HODMEZOVASARHELY-HU":{"name":{"en":"Hodmezovasarhely","ar":"","fr":""},"code":"HODMEZOVASARHELY-HU","countryCode":"HU"},"DUNAUJVAROS-HU":{"name":{"en":"Dunaujvaros","ar":"","fr":""},"code":"DUNAUJVAROS-HU","countryCode":"HU"},"SZIGETSZENTMIKLOS-HU":{"name":{"en":"Szigetszentmiklos","ar":"","fr":""},"code":"SZIGETSZENTMIKLOS-HU","countryCode":"HU"},"CEGLED-HU":{"name":{"en":"Cegled","ar":"","fr":""},"code":"CEGLED-HU","countryCode":"HU"},"MOSONMAGYAROVAR-HU":{"name":{"en":"Mosonmagyarovar","ar":"","fr":""},"code":"MOSONMAGYAROVAR-HU","countryCode":"HU"},"VAC-HU":{"name":{"en":"Vac","ar":"","fr":""},"code":"VAC-HU","countryCode":"HU"},"BAJA-HU":{"name":{"en":"Baja","ar":"","fr":""},"code":"BAJA-HU","countryCode":"HU"},"SALGOTARJAN-HU":{"name":{"en":"Salgotarjan","ar":"","fr":""},"code":"SALGOTARJAN-HU","countryCode":"HU"},"OZD-HU":{"name":{"en":"Ozd","ar":"","fr":""},"code":"OZD-HU","countryCode":"HU"},"SZEKSZARD-HU":{"name":{"en":"Szekszard","ar":"","fr":""},"code":"SZEKSZARD-HU","countryCode":"HU"},"HAJDUBOSZORMENY-HU":{"name":{"en":"Hajduboszormeny","ar":"","fr":""},"code":"HAJDUBOSZORMENY-HU","countryCode":"HU"},"BUDAORS-HU":{"name":{"en":"Budaors","ar":"","fr":""},"code":"BUDAORS-HU","countryCode":"HU"},"KISKUNFELEGYHAZA-HU":{"name":{"en":"Kiskunfelegyhaza","ar":"","fr":""},"code":"KISKUNFELEGYHAZA-HU","countryCode":"HU"},"PAPA-HU":{"name":{"en":"Papa","ar":"","fr":""},"code":"PAPA-HU","countryCode":"HU"},"ESZTERGOM-HU":{"name":{"en":"Esztergom","ar":"","fr":""},"code":"ESZTERGOM-HU","countryCode":"HU"},"SZENTENDRE-HU":{"name":{"en":"Szentendre","ar":"","fr":""},"code":"SZENTENDRE-HU","countryCode":"HU"},"GYULA-HU":{"name":{"en":"Gyula","ar":"","fr":""},"code":"GYULA-HU","countryCode":"HU"},"GYONGYOS-HU":{"name":{"en":"Gyongyos","ar":"","fr":""},"code":"GYONGYOS-HU","countryCode":"HU"},"AJKA-HU":{"name":{"en":"Ajka","ar":"","fr":""},"code":"AJKA-HU","countryCode":"HU"},"KISKUNHALAS-HU":{"name":{"en":"Kiskunhalas","ar":"","fr":""},"code":"KISKUNHALAS-HU","countryCode":"HU"},"JASZBERENY-HU":{"name":{"en":"Jaszbereny","ar":"","fr":""},"code":"JASZBERENY-HU","countryCode":"HU"},"OROSHAZA-HU":{"name":{"en":"Oroshaza","ar":"","fr":""},"code":"OROSHAZA-HU","countryCode":"HU"},"SZENTES-HU":{"name":{"en":"Szentes","ar":"","fr":""},"code":"SZENTES-HU","countryCode":"HU"},"GYAL-HU":{"name":{"en":"Gyal","ar":"","fr":""},"code":"GYAL-HU","countryCode":"HU"},"SIOFOK-HU":{"name":{"en":"Siofok","ar":"","fr":""},"code":"SIOFOK-HU","countryCode":"HU"},"KAZINCBARCIKA-HU":{"name":{"en":"Kazincbarcika","ar":"","fr":""},"code":"KAZINCBARCIKA-HU","countryCode":"HU"},"TATA-HU":{"name":{"en":"Tata","ar":"","fr":""},"code":"TATA-HU","countryCode":"HU"},"DUNAHARASZTI-HU":{"name":{"en":"Dunaharaszti","ar":"","fr":""},"code":"DUNAHARASZTI-HU","countryCode":"HU"},"HAJDUSZOBOSZLO-HU":{"name":{"en":"Hajduszoboszlo","ar":"","fr":""},"code":"HAJDUSZOBOSZLO-HU","countryCode":"HU"},"NAGYKOROS-HU":{"name":{"en":"Nagykoros","ar":"","fr":""},"code":"NAGYKOROS-HU","countryCode":"HU"},"GOD-HU":{"name":{"en":"God","ar":"","fr":""},"code":"GOD-HU","countryCode":"HU"},"MAKO-HU":{"name":{"en":"Mako","ar":"","fr":""},"code":"MAKO-HU","countryCode":"HU"},"KOMLO-HU":{"name":{"en":"Komlo","ar":"","fr":""},"code":"KOMLO-HU","countryCode":"HU"},"VECSES-HU":{"name":{"en":"Vecses","ar":"","fr":""},"code":"VECSES-HU","countryCode":"HU"},"FOT-HU":{"name":{"en":"Fot","ar":"","fr":""},"code":"FOT-HU","countryCode":"HU"},"VERESEGYHAZ-HU":{"name":{"en":"Veresegyhaz","ar":"","fr":""},"code":"VERESEGYHAZ-HU","countryCode":"HU"},"HATVAN-HU":{"name":{"en":"Hatvan","ar":"","fr":""},"code":"HATVAN-HU","countryCode":"HU"},"GYOMRO-HU":{"name":{"en":"Gyomro","ar":"","fr":""},"code":"GYOMRO-HU","countryCode":"HU"},"KOMAROM-HU":{"name":{"en":"Komarom","ar":"","fr":""},"code":"KOMAROM-HU","countryCode":"HU"},"VARPALOTA-HU":{"name":{"en":"Varpalota","ar":"","fr":""},"code":"VARPALOTA-HU","countryCode":"HU"},"TOROKSZENTMIKLOS-HU":{"name":{"en":"Torokszentmiklos","ar":"","fr":""},"code":"TOROKSZENTMIKLOS-HU","countryCode":"HU"},"MONOR-HU":{"name":{"en":"Monor","ar":"","fr":""},"code":"MONOR-HU","countryCode":"HU"},"KARCAG-HU":{"name":{"en":"Karcag","ar":"","fr":""},"code":"KARCAG-HU","countryCode":"HU"},"POMAZ-HU":{"name":{"en":"Pomaz","ar":"","fr":""},"code":"POMAZ-HU","countryCode":"HU"},"SZIGETHALOM-HU":{"name":{"en":"Szigethalom","ar":"","fr":""},"code":"SZIGETHALOM-HU","countryCode":"HU"},"OROSZLANY-HU":{"name":{"en":"Oroszlany","ar":"","fr":""},"code":"OROSZLANY-HU","countryCode":"HU"},"KESZTHELY-HU":{"name":{"en":"Keszthely","ar":"","fr":""},"code":"KESZTHELY-HU","countryCode":"HU"},"SZAZHALOMBATTA-HU":{"name":{"en":"Szazhalombatta","ar":"","fr":""},"code":"SZAZHALOMBATTA-HU","countryCode":"HU"},"PAKS-HU":{"name":{"en":"Paks","ar":"","fr":""},"code":"PAKS-HU","countryCode":"HU"},"BEKES-HU":{"name":{"en":"Bekes","ar":"","fr":""},"code":"BEKES-HU","countryCode":"HU"},"DABAS-HU":{"name":{"en":"Dabas","ar":"","fr":""},"code":"DABAS-HU","countryCode":"HU"},"PECEL-HU":{"name":{"en":"Pecel","ar":"","fr":""},"code":"PECEL-HU","countryCode":"HU"},"MOHACS-HU":{"name":{"en":"Mohacs","ar":"","fr":""},"code":"MOHACS-HU","countryCode":"HU"},"DOMBOVAR-HU":{"name":{"en":"Dombovar","ar":"","fr":""},"code":"DOMBOVAR-HU","countryCode":"HU"},"BALMAZUJVAROS-HU":{"name":{"en":"Balmazujvaros","ar":"","fr":""},"code":"BALMAZUJVAROS-HU","countryCode":"HU"},"HAJDUNANAS-HU":{"name":{"en":"Hajdunanas","ar":"","fr":""},"code":"HAJDUNANAS-HU","countryCode":"HU"},"MEZOTUR-HU":{"name":{"en":"Mezotur","ar":"","fr":""},"code":"MEZOTUR-HU","countryCode":"HU"},"MEZOKOVESD-HU":{"name":{"en":"Mezokovesd","ar":"","fr":""},"code":"MEZOKOVESD-HU","countryCode":"HU"},"TISZAUJVAROS-HU":{"name":{"en":"Tiszaujvaros","ar":"","fr":""},"code":"TISZAUJVAROS-HU","countryCode":"HU"},"BUDAKESZI-HU":{"name":{"en":"Budakeszi","ar":"","fr":""},"code":"BUDAKESZI-HU","countryCode":"HU"},"CSONGRAD-HU":{"name":{"en":"Csongrad","ar":"","fr":""},"code":"CSONGRAD-HU","countryCode":"HU"},"MATESZALKA-HU":{"name":{"en":"Mateszalka","ar":"","fr":""},"code":"MATESZALKA-HU","countryCode":"HU"},"BIATORBAGY-HU":{"name":{"en":"Biatorbagy","ar":"","fr":""},"code":"BIATORBAGY-HU","countryCode":"HU"},"SARVAR-HU":{"name":{"en":"Sarvar","ar":"","fr":""},"code":"SARVAR-HU","countryCode":"HU"},"KISVARDA-HU":{"name":{"en":"Kisvarda","ar":"","fr":""},"code":"KISVARDA-HU","countryCode":"HU"},"TOROKBALINT-HU":{"name":{"en":"Torokbalint","ar":"","fr":""},"code":"TOROKBALINT-HU","countryCode":"HU"},"ABONY-HU":{"name":{"en":"Abony","ar":"","fr":""},"code":"ABONY-HU","countryCode":"HU"},"KALOCSA-HU":{"name":{"en":"Kalocsa","ar":"","fr":""},"code":"KALOCSA-HU","countryCode":"HU"},"PILISVOROSVAR-HU":{"name":{"en":"Pilisvorosvar","ar":"","fr":""},"code":"PILISVOROSVAR-HU","countryCode":"HU"},"SZARVAS-HU":{"name":{"en":"Szarvas","ar":"","fr":""},"code":"SZARVAS-HU","countryCode":"HU"},"TAPOLCA-HU":{"name":{"en":"Tapolca","ar":"","fr":""},"code":"TAPOLCA-HU","countryCode":"HU"},"BERETTYOUJFALU-HU":{"name":{"en":"Berettyoujfalu","ar":"","fr":""},"code":"BERETTYOUJFALU-HU","countryCode":"HU"},"BALASSAGYARMAT-HU":{"name":{"en":"Balassagyarmat","ar":"","fr":""},"code":"BALASSAGYARMAT-HU","countryCode":"HU"},"HAJDUSAMSON-HU":{"name":{"en":"Hajdusamson","ar":"","fr":""},"code":"HAJDUSAMSON-HU","countryCode":"HU"},"KEREPESTARCSA-HU":{"name":{"en":"Kerepestarcsa","ar":"","fr":""},"code":"KEREPESTARCSA-HU","countryCode":"HU"},"MOR-HU":{"name":{"en":"Mor","ar":"","fr":""},"code":"MOR-HU","countryCode":"HU"},"ALBERTIRSA-HU":{"name":{"en":"Albertirsa","ar":"","fr":""},"code":"ALBERTIRSA-HU","countryCode":"HU"},"GARDONY-HU":{"name":{"en":"Gardony","ar":"","fr":""},"code":"GARDONY-HU","countryCode":"HU"},"KISKOROS-HU":{"name":{"en":"Kiskoros","ar":"","fr":""},"code":"KISKOROS-HU","countryCode":"HU"},"PUSPOKLADANY-HU":{"name":{"en":"Puspokladany","ar":"","fr":""},"code":"PUSPOKLADANY-HU","countryCode":"HU"},"SATORALJAUJHELY-HU":{"name":{"en":"Satoraljaujhely","ar":"","fr":""},"code":"SATORALJAUJHELY-HU","countryCode":"HU"},"HAJDUHADHAZ-HU":{"name":{"en":"Hajduhadhaz","ar":"","fr":""},"code":"HAJDUHADHAZ-HU","countryCode":"HU"},"BALATONFURED-HU":{"name":{"en":"Balatonfured","ar":"","fr":""},"code":"BALATONFURED-HU","countryCode":"HU"},"ULLO-HU":{"name":{"en":"Ullo","ar":"","fr":""},"code":"ULLO-HU","countryCode":"HU"},"MAGLOD-HU":{"name":{"en":"Maglod","ar":"","fr":""},"code":"MAGLOD-HU","countryCode":"HU"},"TISZAVASVARI-HU":{"name":{"en":"Tiszavasvari","ar":"","fr":""},"code":"TISZAVASVARI-HU","countryCode":"HU"},"UJFEHERTO-HU":{"name":{"en":"Ujfeherto","ar":"","fr":""},"code":"UJFEHERTO-HU","countryCode":"HU"},"BONYHAD-HU":{"name":{"en":"Bonyhad","ar":"","fr":""},"code":"BONYHAD-HU","countryCode":"HU"},"GYOMAENDROD-HU":{"name":{"en":"Gyomaendrod","ar":"","fr":""},"code":"GYOMAENDROD-HU","countryCode":"HU"},"BUDAKALASZ-HU":{"name":{"en":"Budakalasz","ar":"","fr":""},"code":"BUDAKALASZ-HU","countryCode":"HU"},"NAGYKATA-HU":{"name":{"en":"Nagykata","ar":"","fr":""},"code":"NAGYKATA-HU","countryCode":"HU"},"HALASZTELEK-HU":{"name":{"en":"Halasztelek","ar":"","fr":""},"code":"HALASZTELEK-HU","countryCode":"HU"},"PILIS-HU":{"name":{"en":"Pilis","ar":"","fr":""},"code":"PILIS-HU","countryCode":"HU"},"KOSZEG-HU":{"name":{"en":"Koszeg","ar":"","fr":""},"code":"KOSZEG-HU","countryCode":"HU"},"KISKUNMAJSA-HU":{"name":{"en":"Kiskunmajsa","ar":"","fr":""},"code":"KISKUNMAJSA-HU","countryCode":"HU"},"TISZAKECSKE-HU":{"name":{"en":"Tiszakecske","ar":"","fr":""},"code":"TISZAKECSKE-HU","countryCode":"HU"},"LAJOSMIZSE-HU":{"name":{"en":"Lajosmizse","ar":"","fr":""},"code":"LAJOSMIZSE-HU","countryCode":"HU"},"ISASZEG-HU":{"name":{"en":"Isaszeg","ar":"","fr":""},"code":"ISASZEG-HU","countryCode":"HU"},"DIOSD-HU":{"name":{"en":"Diosd","ar":"","fr":""},"code":"DIOSD-HU","countryCode":"HU"},"SARBOGARD-HU":{"name":{"en":"Sarbogard","ar":"","fr":""},"code":"SARBOGARD-HU","countryCode":"HU"},"DOROG-HU":{"name":{"en":"Dorog","ar":"","fr":""},"code":"DOROG-HU","countryCode":"HU"},"NYIRBATOR-HU":{"name":{"en":"Nyirbator","ar":"","fr":""},"code":"NYIRBATOR-HU","countryCode":"HU"},"TOKOL-HU":{"name":{"en":"Tokol","ar":"","fr":""},"code":"TOKOL-HU","countryCode":"HU"},"BATONYTERENYE-HU":{"name":{"en":"Batonyterenye","ar":"","fr":""},"code":"BATONYTERENYE-HU","countryCode":"HU"},"SAJOSZENTPETER-HU":{"name":{"en":"Sajoszentpeter","ar":"","fr":""},"code":"SAJOSZENTPETER-HU","countryCode":"HU"},"BICSKE-HU":{"name":{"en":"Bicske","ar":"","fr":""},"code":"BICSKE-HU","countryCode":"HU"},"RACKEVE-HU":{"name":{"en":"Rackeve","ar":"","fr":""},"code":"RACKEVE-HU","countryCode":"HU"},"SOLYMAR-HU":{"name":{"en":"Solymar","ar":"","fr":""},"code":"SOLYMAR-HU","countryCode":"HU"},"TISZAFURED-HU":{"name":{"en":"Tiszafured","ar":"","fr":""},"code":"TISZAFURED-HU","countryCode":"HU"},"SAROSPATAK-HU":{"name":{"en":"Sarospatak","ar":"","fr":""},"code":"SAROSPATAK-HU","countryCode":"HU"},"MARCALI-HU":{"name":{"en":"Marcali","ar":"","fr":""},"code":"MARCALI-HU","countryCode":"HU"},"TOLNA-HU":{"name":{"en":"Tolna","ar":"","fr":""},"code":"TOLNA-HU","countryCode":"HU"},"TARNOK-HU":{"name":{"en":"Tarnok","ar":"","fr":""},"code":"TARNOK-HU","countryCode":"HU"},"KORMEND-HU":{"name":{"en":"Kormend","ar":"","fr":""},"code":"KORMEND-HU","countryCode":"HU"},"CSOMOR-HU":{"name":{"en":"Csomor","ar":"","fr":""},"code":"CSOMOR-HU","countryCode":"HU"},"KISUJSZALLAS-HU":{"name":{"en":"Kisujszallas","ar":"","fr":""},"code":"KISUJSZALLAS-HU","countryCode":"HU"},"TISZAFOLDVAR-HU":{"name":{"en":"Tiszafoldvar","ar":"","fr":""},"code":"TISZAFOLDVAR-HU","countryCode":"HU"},"KAPUVAR-HU":{"name":{"en":"Kapuvar","ar":"","fr":""},"code":"KAPUVAR-HU","countryCode":"HU"},"BALATONALMADI-HU":{"name":{"en":"Balatonalmadi","ar":"","fr":""},"code":"BALATONALMADI-HU","countryCode":"HU"},"OCSA-HU":{"name":{"en":"Ocsa","ar":"","fr":""},"code":"OCSA-HU","countryCode":"HU"},"HEVES-HU":{"name":{"en":"Heves","ar":"","fr":""},"code":"HEVES-HU","countryCode":"HU"},"CELLDOMOLK-HU":{"name":{"en":"Celldomolk","ar":"","fr":""},"code":"CELLDOMOLK-HU","countryCode":"HU"},"BARCS-HU":{"name":{"en":"Barcs","ar":"","fr":""},"code":"BARCS-HU","countryCode":"HU"},"CSORNA-HU":{"name":{"en":"Csorna","ar":"","fr":""},"code":"CSORNA-HU","countryCode":"HU"},"SZIGETVAR-HU":{"name":{"en":"Szigetvar","ar":"","fr":""},"code":"SZIGETVAR-HU","countryCode":"HU"},"ERDOKERTES-HU":{"name":{"en":"Erdokertes","ar":"","fr":""},"code":"ERDOKERTES-HU","countryCode":"HU"},"MEZOBERENY-HU":{"name":{"en":"Mezobereny","ar":"","fr":""},"code":"MEZOBERENY-HU","countryCode":"HU"},"NAGYATAD-HU":{"name":{"en":"Nagyatad","ar":"","fr":""},"code":"NAGYATAD-HU","countryCode":"HU"},"EDELENY-HU":{"name":{"en":"Edeleny","ar":"","fr":""},"code":"EDELENY-HU","countryCode":"HU"},"SARKAD-HU":{"name":{"en":"Sarkad","ar":"","fr":""},"code":"SARKAD-HU","countryCode":"HU"},"NAGYKALLO-HU":{"name":{"en":"Nagykallo","ar":"","fr":""},"code":"NAGYKALLO-HU","countryCode":"HU"},"KISKUNLACHAZA-HU":{"name":{"en":"Kiskunlachaza","ar":"","fr":""},"code":"KISKUNLACHAZA-HU","countryCode":"HU"},"DUNAVARSANY-HU":{"name":{"en":"Dunavarsany","ar":"","fr":""},"code":"DUNAVARSANY-HU","countryCode":"HU"},"NAGYKOVACSI-HU":{"name":{"en":"Nagykovacsi","ar":"","fr":""},"code":"NAGYKOVACSI-HU","countryCode":"HU"},"SIKLOS-HU":{"name":{"en":"Siklos","ar":"","fr":""},"code":"SIKLOS-HU","countryCode":"HU"},"PILISCSABA-HU":{"name":{"en":"Piliscsaba","ar":"","fr":""},"code":"PILISCSABA-HU","countryCode":"HU"},"PASZTO-HU":{"name":{"en":"Paszto","ar":"","fr":""},"code":"PASZTO-HU","countryCode":"HU"}}}