{"name":{"en":"Syria","fr":"Syrie","ar":"سوريا"},"code":"SY","capital":"Damascus","language":"Arabic","dialling":{"calling_code":["963"],"national_prefix":"0","national_number_lengths":[7,8,9],"national_destination_code_lengths":[2],"international_prefix":"00"},"currency":{"name":"Syrian Pound","code":"SYP"},"cities":{"DAMASCUS-SY":{"name":{"en":"Damascus","ar":"","fr":""},"code":"DAMASCUS-SY","countryCode":"SY"},"ALEPPO-SY":{"name":{"en":"Aleppo","ar":"","fr":""},"code":"ALEPPO-SY","countryCode":"SY"},"HOMS-SY":{"name":{"en":"Homs","ar":"","fr":""},"code":"HOMS-SY","countryCode":"SY"},"LATAKIA-SY":{"name":{"en":"Latakia","ar":"","fr":""},"code":"LATAKIA-SY","countryCode":"SY"},"HAMAH-SY":{"name":{"en":"Hamah","ar":"","fr":""},"code":"HAMAH-SY","countryCode":"SY"},"AR-RAQQAH-SY":{"name":{"en":"Ar Raqqah","ar":"","fr":""},"code":"AR-RAQQAH-SY","countryCode":"SY"},"DAYR-AZ-ZAWR-SY":{"name":{"en":"Dayr az Zawr","ar":"","fr":""},"code":"DAYR-AZ-ZAWR-SY","countryCode":"SY"},"AL-HASAKAH-SY":{"name":{"en":"Al Hasakah","ar":"","fr":""},"code":"AL-HASAKAH-SY","countryCode":"SY"},"AL-QAMISHLI-SY":{"name":{"en":"Al Qamishli","ar":"","fr":""},"code":"AL-QAMISHLI-SY","countryCode":"SY"},"IDLIB-SY":{"name":{"en":"Idlib","ar":"","fr":""},"code":"IDLIB-SY","countryCode":"SY"},"DAR`A-SY":{"name":{"en":"Dar`a","ar":"","fr":""},"code":"DAR`A-SY","countryCode":"SY"},"QABR-AS-SITT-SY":{"name":{"en":"Qabr as Sitt","ar":"","fr":""},"code":"QABR-AS-SITT-SY","countryCode":"SY"},"DUMA-SY":{"name":{"en":"Duma","ar":"","fr":""},"code":"DUMA-SY","countryCode":"SY"},"JARAMANA-SY":{"name":{"en":"Jaramana","ar":"","fr":""},"code":"JARAMANA-SY","countryCode":"SY"},"AS-SALAMIYAH-SY":{"name":{"en":"As Salamiyah","ar":"","fr":""},"code":"AS-SALAMIYAH-SY","countryCode":"SY"},"AS-SAFIRAH-SY":{"name":{"en":"As Safirah","ar":"","fr":""},"code":"AS-SAFIRAH-SY","countryCode":"SY"},"AL-HAJAR-AL-ASWAD-SY":{"name":{"en":"Al Hajar al Aswad","ar":"","fr":""},"code":"AL-HAJAR-AL-ASWAD-SY","countryCode":"SY"},"MA`ARRAT-AN-NU`MAN-SY":{"name":{"en":"Ma`arrat an Nu`man","ar":"","fr":""},"code":"MA`ARRAT-AN-NU`MAN-SY","countryCode":"SY"},"TARTUS-SY":{"name":{"en":"Tartus","ar":"","fr":""},"code":"TARTUS-SY","countryCode":"SY"},"DARAYYA-SY":{"name":{"en":"Darayya","ar":"","fr":""},"code":"DARAYYA-SY","countryCode":"SY"},"ATH-THAWRAH-SY":{"name":{"en":"Ath Thawrah","ar":"","fr":""},"code":"ATH-THAWRAH-SY","countryCode":"SY"},"MANBIJ-SY":{"name":{"en":"Manbij","ar":"","fr":""},"code":"MANBIJ-SY","countryCode":"SY"},"JABLAH-SY":{"name":{"en":"Jablah","ar":"","fr":""},"code":"JABLAH-SY","countryCode":"SY"},"AL-QURAYYA-SY":{"name":{"en":"Al Qurayya","ar":"","fr":""},"code":"AL-QURAYYA-SY","countryCode":"SY"},"AS-SUWAYDA'-SY":{"name":{"en":"As Suwayda'","ar":"","fr":""},"code":"AS-SUWAYDA'-SY","countryCode":"SY"},"NAWA-SY":{"name":{"en":"Nawa","ar":"","fr":""},"code":"NAWA-SY","countryCode":"SY"},"AT-TALL-SY":{"name":{"en":"At Tall","ar":"","fr":""},"code":"AT-TALL-SY","countryCode":"SY"},"AR-RASTAN-SY":{"name":{"en":"Ar Rastan","ar":"","fr":""},"code":"AR-RASTAN-SY","countryCode":"SY"},"KHAN-SHAYKHUN-SY":{"name":{"en":"Khan Shaykhun","ar":"","fr":""},"code":"KHAN-SHAYKHUN-SY","countryCode":"SY"},"AN-NABK-SY":{"name":{"en":"An Nabk","ar":"","fr":""},"code":"AN-NABK-SY","countryCode":"SY"},"ALBU-KAMAL-SY":{"name":{"en":"Albu Kamal","ar":"","fr":""},"code":"ALBU-KAMAL-SY","countryCode":"SY"},"TADMUR-SY":{"name":{"en":"Tadmur","ar":"","fr":""},"code":"TADMUR-SY","countryCode":"SY"},"BABILA-SY":{"name":{"en":"Babila","ar":"","fr":""},"code":"BABILA-SY","countryCode":"SY"},"AL-MAYADIN-SY":{"name":{"en":"Al Mayadin","ar":"","fr":""},"code":"AL-MAYADIN-SY","countryCode":"SY"},"ASH-SHAYKH-BADR-SY":{"name":{"en":"Ash Shaykh Badr","ar":"","fr":""},"code":"ASH-SHAYKH-BADR-SY","countryCode":"SY"},"`AMUDA-SY":{"name":{"en":"`Amuda","ar":"","fr":""},"code":"`AMUDA-SY","countryCode":"SY"},"YABRUD-SY":{"name":{"en":"Yabrud","ar":"","fr":""},"code":"YABRUD-SY","countryCode":"SY"},"AL-QUSAYR-SY":{"name":{"en":"Al Qusayr","ar":"","fr":""},"code":"AL-QUSAYR-SY","countryCode":"SY"},"HARASTA-SY":{"name":{"en":"Harasta","ar":"","fr":""},"code":"HARASTA-SY","countryCode":"SY"},"TALLBISAH-SY":{"name":{"en":"Tallbisah","ar":"","fr":""},"code":"TALLBISAH-SY","countryCode":"SY"},"`AYN-AL-`ARAB-SY":{"name":{"en":"`Ayn al `Arab","ar":"","fr":""},"code":"`AYN-AL-`ARAB-SY","countryCode":"SY"},"ZAMALKA-SY":{"name":{"en":"Zamalka","ar":"","fr":""},"code":"ZAMALKA-SY","countryCode":"SY"},"JISR-ASH-SHUGHUR-SY":{"name":{"en":"Jisr ash Shughur","ar":"","fr":""},"code":"JISR-ASH-SHUGHUR-SY","countryCode":"SY"},"AL-KISWAH-SY":{"name":{"en":"Al Kiswah","ar":"","fr":""},"code":"AL-KISWAH-SY","countryCode":"SY"},"BANIYAS-SY":{"name":{"en":"Baniyas","ar":"","fr":""},"code":"BANIYAS-SY","countryCode":"SY"},"TADIF-SY":{"name":{"en":"Tadif","ar":"","fr":""},"code":"TADIF-SY","countryCode":"SY"},"JAYRUD-SY":{"name":{"en":"Jayrud","ar":"","fr":""},"code":"JAYRUD-SY","countryCode":"SY"},"SARAQIB-SY":{"name":{"en":"Saraqib","ar":"","fr":""},"code":"SARAQIB-SY","countryCode":"SY"},"AL-MALIKIYAH-SY":{"name":{"en":"Al Malikiyah","ar":"","fr":""},"code":"AL-MALIKIYAH-SY","countryCode":"SY"},"AL-GHIZLANIYAH-SY":{"name":{"en":"Al Ghizlaniyah","ar":"","fr":""},"code":"AL-GHIZLANIYAH-SY","countryCode":"SY"},"HAJIN-SY":{"name":{"en":"Hajin","ar":"","fr":""},"code":"HAJIN-SY","countryCode":"SY"},"AL-QARYATAYN-SY":{"name":{"en":"Al Qaryatayn","ar":"","fr":""},"code":"AL-QARYATAYN-SY","countryCode":"SY"},"MA`ARRATMISRIN-SY":{"name":{"en":"Ma`arratmisrin","ar":"","fr":""},"code":"MA`ARRATMISRIN-SY","countryCode":"SY"},"MASYAF-SY":{"name":{"en":"Masyaf","ar":"","fr":""},"code":"MASYAF-SY","countryCode":"SY"},"`AFRIN-SY":{"name":{"en":"`Afrin","ar":"","fr":""},"code":"`AFRIN-SY","countryCode":"SY"},"TALLKALAKH-SY":{"name":{"en":"Tallkalakh","ar":"","fr":""},"code":"TALLKALAKH-SY","countryCode":"SY"},"DAYR-HAFIR-SY":{"name":{"en":"Dayr Hafir","ar":"","fr":""},"code":"DAYR-HAFIR-SY","countryCode":"SY"},"SALKHAD-SY":{"name":{"en":"Salkhad","ar":"","fr":""},"code":"SALKHAD-SY","countryCode":"SY"},"TALL-SALHAB-SY":{"name":{"en":"Tall Salhab","ar":"","fr":""},"code":"TALL-SALHAB-SY","countryCode":"SY"},"QADSAYYA-SY":{"name":{"en":"Qadsayya","ar":"","fr":""},"code":"QADSAYYA-SY","countryCode":"SY"},"TAFAS-SY":{"name":{"en":"Tafas","ar":"","fr":""},"code":"TAFAS-SY","countryCode":"SY"},"SAFITA-SY":{"name":{"en":"Safita","ar":"","fr":""},"code":"SAFITA-SY","countryCode":"SY"},"JASIM-SY":{"name":{"en":"Jasim","ar":"","fr":""},"code":"JASIM-SY","countryCode":"SY"},"I`ZAZ-SY":{"name":{"en":"I`zaz","ar":"","fr":""},"code":"I`ZAZ-SY","countryCode":"SY"},"INKHIL-SY":{"name":{"en":"Inkhil","ar":"","fr":""},"code":"INKHIL-SY","countryCode":"SY"},"AR-RUHAYBAH-SY":{"name":{"en":"Ar Ruhaybah","ar":"","fr":""},"code":"AR-RUHAYBAH-SY","countryCode":"SY"},"KAFR-NUBL-SY":{"name":{"en":"Kafr Nubl","ar":"","fr":""},"code":"KAFR-NUBL-SY","countryCode":"SY"},"RA'S-AL-`AYN-SY":{"name":{"en":"Ra's al `Ayn","ar":"","fr":""},"code":"RA'S-AL-`AYN-SY","countryCode":"SY"},"SURAN-SY":{"name":{"en":"Suran","ar":"","fr":""},"code":"SURAN-SY","countryCode":"SY"},"YALDA-SY":{"name":{"en":"Yalda","ar":"","fr":""},"code":"YALDA-SY","countryCode":"SY"},"TALL-RIF`AT-SY":{"name":{"en":"Tall Rif`at","ar":"","fr":""},"code":"TALL-RIF`AT-SY","countryCode":"SY"},"AL-QUTAYFAH-SY":{"name":{"en":"Al Qutayfah","ar":"","fr":""},"code":"AL-QUTAYFAH-SY","countryCode":"SY"},"AZ-ZABADANI-SY":{"name":{"en":"Az Zabadani","ar":"","fr":""},"code":"AZ-ZABADANI-SY","countryCode":"SY"},"AS-SANAMAYN-SY":{"name":{"en":"As Sanamayn","ar":"","fr":""},"code":"AS-SANAMAYN-SY","countryCode":"SY"},"SIQBA-SY":{"name":{"en":"Siqba","ar":"","fr":""},"code":"SIQBA-SY","countryCode":"SY"},"SAYDNAYA-SY":{"name":{"en":"Saydnaya","ar":"","fr":""},"code":"SAYDNAYA-SY","countryCode":"SY"},"TALL-SHIHAB-SY":{"name":{"en":"Tall Shihab","ar":"","fr":""},"code":"TALL-SHIHAB-SY","countryCode":"SY"},"TAYYIBAT-AL-IMAM-SY":{"name":{"en":"Tayyibat al Imam","ar":"","fr":""},"code":"TAYYIBAT-AL-IMAM-SY","countryCode":"SY"},"SUBAYKHAN-SY":{"name":{"en":"Subaykhan","ar":"","fr":""},"code":"SUBAYKHAN-SY","countryCode":"SY"},"SALQIN-SY":{"name":{"en":"Salqin","ar":"","fr":""},"code":"SALQIN-SY","countryCode":"SY"},"QATANA-SY":{"name":{"en":"Qatana","ar":"","fr":""},"code":"QATANA-SY","countryCode":"SY"},"KAFR-BATNA-SY":{"name":{"en":"Kafr Batna","ar":"","fr":""},"code":"KAFR-BATNA-SY","countryCode":"SY"},"HARIM-SY":{"name":{"en":"Harim","ar":"","fr":""},"code":"HARIM-SY","countryCode":"SY"},"BINNISH-SY":{"name":{"en":"Binnish","ar":"","fr":""},"code":"BINNISH-SY","countryCode":"SY"},"NUBL-SY":{"name":{"en":"Nubl","ar":"","fr":""},"code":"NUBL-SY","countryCode":"SY"},"`ADRA-SY":{"name":{"en":"`Adra","ar":"","fr":""},"code":"`ADRA-SY","countryCode":"SY"},"KAFR-LAHA-SY":{"name":{"en":"Kafr Laha","ar":"","fr":""},"code":"KAFR-LAHA-SY","countryCode":"SY"},"BUSRA-ASH-SHAM-SY":{"name":{"en":"Busra ash Sham","ar":"","fr":""},"code":"BUSRA-ASH-SHAM-SY","countryCode":"SY"},"IZRA-SY":{"name":{"en":"Izra","ar":"","fr":""},"code":"IZRA-SY","countryCode":"SY"},"ZAKIYAH-SY":{"name":{"en":"Zakiyah","ar":"","fr":""},"code":"ZAKIYAH-SY","countryCode":"SY"},"TALL-`ARAN-SY":{"name":{"en":"Tall `Aran","ar":"","fr":""},"code":"TALL-`ARAN-SY","countryCode":"SY"},"MUHRADAH-SY":{"name":{"en":"Muhradah","ar":"","fr":""},"code":"MUHRADAH-SY","countryCode":"SY"},"AL-`ASHARAH-SY":{"name":{"en":"Al `Asharah","ar":"","fr":""},"code":"AL-`ASHARAH-SY","countryCode":"SY"},"MANIN-SY":{"name":{"en":"Manin","ar":"","fr":""},"code":"MANIN-SY","countryCode":"SY"},"AS-SUQAYLIBIYAH-SY":{"name":{"en":"As Suqaylibiyah","ar":"","fr":""},"code":"AS-SUQAYLIBIYAH-SY","countryCode":"SY"},"AL-HARAH-SY":{"name":{"en":"Al Harah","ar":"","fr":""},"code":"AL-HARAH-SY","countryCode":"SY"},"KAFR-ZAYTA-SY":{"name":{"en":"Kafr Zayta","ar":"","fr":""},"code":"KAFR-ZAYTA-SY","countryCode":"SY"},"MARI`-SY":{"name":{"en":"Mari`","ar":"","fr":""},"code":"MARI`-SY","countryCode":"SY"},"SHAHBA-SY":{"name":{"en":"Shahba","ar":"","fr":""},"code":"SHAHBA-SY","countryCode":"SY"},"AL-LATAMINAH-SY":{"name":{"en":"Al Lataminah","ar":"","fr":""},"code":"AL-LATAMINAH-SY","countryCode":"SY"},"KHIRBAT-GHAZALAH-SY":{"name":{"en":"Khirbat Ghazalah","ar":"","fr":""},"code":"KHIRBAT-GHAZALAH-SY","countryCode":"SY"},"AS-SUKHNAH-SY":{"name":{"en":"As Sukhnah","ar":"","fr":""},"code":"AS-SUKHNAH-SY","countryCode":"SY"},"TASIL-SY":{"name":{"en":"Tasil","ar":"","fr":""},"code":"TASIL-SY","countryCode":"SY"},"ASH-SHADDADAH-SY":{"name":{"en":"Ash Shaddadah","ar":"","fr":""},"code":"ASH-SHADDADAH-SY","countryCode":"SY"},"AL-MU`ABBADAH-SY":{"name":{"en":"Al Mu`abbadah","ar":"","fr":""},"code":"AL-MU`ABBADAH-SY","countryCode":"SY"},"BAYT-SAHAM-SY":{"name":{"en":"Bayt Saham","ar":"","fr":""},"code":"BAYT-SAHAM-SY","countryCode":"SY"},"MASKANAH-SY":{"name":{"en":"Maskanah","ar":"","fr":""},"code":"MASKANAH-SY","countryCode":"SY"},"KULJIBRIN-SY":{"name":{"en":"Kuljibrin","ar":"","fr":""},"code":"KULJIBRIN-SY","countryCode":"SY"},"SARMADA-SY":{"name":{"en":"Sarmada","ar":"","fr":""},"code":"SARMADA-SY","countryCode":"SY"},"TALL-ABYAD-SY":{"name":{"en":"Tall Abyad","ar":"","fr":""},"code":"TALL-ABYAD-SY","countryCode":"SY"},"SARMIN-SY":{"name":{"en":"Sarmin","ar":"","fr":""},"code":"SARMIN-SY","countryCode":"SY"},"MURAK-SY":{"name":{"en":"Murak","ar":"","fr":""},"code":"MURAK-SY","countryCode":"SY"},"AL-MU`ADDAMIYAH-SY":{"name":{"en":"Al Mu`addamiyah","ar":"","fr":""},"code":"AL-MU`ADDAMIYAH-SY","countryCode":"SY"},"SAHNAYA-SY":{"name":{"en":"Sahnaya","ar":"","fr":""},"code":"SAHNAYA-SY","countryCode":"SY"},"KANAKIR-SY":{"name":{"en":"Kanakir","ar":"","fr":""},"code":"KANAKIR-SY","countryCode":"SY"},"JINDAYRIS-SY":{"name":{"en":"Jindayris","ar":"","fr":""},"code":"JINDAYRIS-SY","countryCode":"SY"},"DARAT-`IZZAH-SY":{"name":{"en":"Darat `Izzah","ar":"","fr":""},"code":"DARAT-`IZZAH-SY","countryCode":"SY"},"KAFR-NABUDAH-SY":{"name":{"en":"Kafr Nabudah","ar":"","fr":""},"code":"KAFR-NABUDAH-SY","countryCode":"SY"},"BUSRA-AL-HARIR-SY":{"name":{"en":"Busra al Harir","ar":"","fr":""},"code":"BUSRA-AL-HARIR-SY","countryCode":"SY"},"AD-DURAYKISH-SY":{"name":{"en":"Ad Duraykish","ar":"","fr":""},"code":"AD-DURAYKISH-SY","countryCode":"SY"},"SHIN-SY":{"name":{"en":"Shin","ar":"","fr":""},"code":"SHIN-SY","countryCode":"SY"},"QAL`AT-AL-MADIQ-SY":{"name":{"en":"Qal`at al Madiq","ar":"","fr":""},"code":"QAL`AT-AL-MADIQ-SY","countryCode":"SY"},"AL-MUZAYRIB-SY":{"name":{"en":"Al Muzayrib","ar":"","fr":""},"code":"AL-MUZAYRIB-SY","countryCode":"SY"},"QARAH-SY":{"name":{"en":"Qarah","ar":"","fr":""},"code":"QARAH-SY","countryCode":"SY"},"MI`RABAH-SY":{"name":{"en":"Mi`rabah","ar":"","fr":""},"code":"MI`RABAH-SY","countryCode":"SY"},"HAWSH-AL-BAHDALIYAH-SY":{"name":{"en":"Hawsh al Bahdaliyah","ar":"","fr":""},"code":"HAWSH-AL-BAHDALIYAH-SY","countryCode":"SY"},"KAFR-RUMA-SY":{"name":{"en":"Kafr Ruma","ar":"","fr":""},"code":"KAFR-RUMA-SY","countryCode":"SY"},"KAFR-BUHUM-SY":{"name":{"en":"Kafr Buhum","ar":"","fr":""},"code":"KAFR-BUHUM-SY","countryCode":"SY"},"TALL-DHAHAB-SY":{"name":{"en":"Tall Dhahab","ar":"","fr":""},"code":"TALL-DHAHAB-SY","countryCode":"SY"},"`ANADAN-SY":{"name":{"en":"`Anadan","ar":"","fr":""},"code":"`ANADAN-SY","countryCode":"SY"},"GHABAGHIB-SY":{"name":{"en":"Ghabaghib","ar":"","fr":""},"code":"GHABAGHIB-SY","countryCode":"SY"},"JARABULUS-SY":{"name":{"en":"Jarabulus","ar":"","fr":""},"code":"JARABULUS-SY","countryCode":"SY"},"SAYDA-SY":{"name":{"en":"Sayda","ar":"","fr":""},"code":"SAYDA-SY","countryCode":"SY"},"MAHIN-SY":{"name":{"en":"Mahin","ar":"","fr":""},"code":"MAHIN-SY","countryCode":"SY"},"DAYR-`ATIYAH-SY":{"name":{"en":"Dayr `Atiyah","ar":"","fr":""},"code":"DAYR-`ATIYAH-SY","countryCode":"SY"},"AS-SABBURAH-SY":{"name":{"en":"As Sabburah","ar":"","fr":""},"code":"AS-SABBURAH-SY","countryCode":"SY"},"KHATTAB-SY":{"name":{"en":"Khattab","ar":"","fr":""},"code":"KHATTAB-SY","countryCode":"SY"},"JARJANAZ-SY":{"name":{"en":"Jarjanaz","ar":"","fr":""},"code":"JARJANAZ-SY","countryCode":"SY"},"BAGHUZ-FAWQANI-SY":{"name":{"en":"Baghuz Fawqani","ar":"","fr":""},"code":"BAGHUZ-FAWQANI-SY","countryCode":"SY"},"AL-ATARIB-SY":{"name":{"en":"Al Atarib","ar":"","fr":""},"code":"AL-ATARIB-SY","countryCode":"SY"},"`UTAYBAH-SY":{"name":{"en":"`Utaybah","ar":"","fr":""},"code":"`UTAYBAH-SY","countryCode":"SY"},"AL-KARAK-SY":{"name":{"en":"Al Karak","ar":"","fr":""},"code":"AL-KARAK-SY","countryCode":"SY"},"AL-MUSAYFIRAH-SY":{"name":{"en":"Al Musayfirah","ar":"","fr":""},"code":"AL-MUSAYFIRAH-SY","countryCode":"SY"},"TURMANIN-SY":{"name":{"en":"Turmanin","ar":"","fr":""},"code":"TURMANIN-SY","countryCode":"SY"},"BARAH-SY":{"name":{"en":"Barah","ar":"","fr":""},"code":"BARAH-SY","countryCode":"SY"},"ARMANAZ-SY":{"name":{"en":"Armanaz","ar":"","fr":""},"code":"ARMANAZ-SY","countryCode":"SY"},"MA`RABA-SY":{"name":{"en":"Ma`raba","ar":"","fr":""},"code":"MA`RABA-SY","countryCode":"SY"},"MIHQAN-SY":{"name":{"en":"Mihqan","ar":"","fr":""},"code":"MIHQAN-SY","countryCode":"SY"},"KAFR-TAKHARIM-SY":{"name":{"en":"Kafr Takharim","ar":"","fr":""},"code":"KAFR-TAKHARIM-SY","countryCode":"SY"},"AL-HAMAH-SY":{"name":{"en":"Al Hamah","ar":"","fr":""},"code":"AL-HAMAH-SY","countryCode":"SY"},"AN-NAYRAB-SY":{"name":{"en":"An Nayrab","ar":"","fr":""},"code":"AN-NAYRAB-SY","countryCode":"SY"},"MAHAJJAH-SY":{"name":{"en":"Mahajjah","ar":"","fr":""},"code":"MAHAJJAH-SY","countryCode":"SY"},"GHARIYAH-AL-GHARBIYAH-SY":{"name":{"en":"Ghariyah al Gharbiyah","ar":"","fr":""},"code":"GHARIYAH-AL-GHARBIYAH-SY","countryCode":"SY"},"GHABRAH-SY":{"name":{"en":"Ghabrah","ar":"","fr":""},"code":"GHABRAH-SY","countryCode":"SY"},"HAS-SY":{"name":{"en":"Has","ar":"","fr":""},"code":"HAS-SY","countryCode":"SY"},"MUH-HASAN-SY":{"name":{"en":"Muh Hasan","ar":"","fr":""},"code":"MUH-HASAN-SY","countryCode":"SY"},"JISRAYN-SY":{"name":{"en":"Jisrayn","ar":"","fr":""},"code":"JISRAYN-SY","countryCode":"SY"},"MADAYA-SY":{"name":{"en":"Madaya","ar":"","fr":""},"code":"MADAYA-SY","countryCode":"SY"},"ABU-KHASHAB-SY":{"name":{"en":"Abu Khashab","ar":"","fr":""},"code":"ABU-KHASHAB-SY","countryCode":"SY"},"DHIBAN-SY":{"name":{"en":"Dhiban","ar":"","fr":""},"code":"DHIBAN-SY","countryCode":"SY"},"AL-YADUDAH-SY":{"name":{"en":"Al Yadudah","ar":"","fr":""},"code":"AL-YADUDAH-SY","countryCode":"SY"},"KAFR-SAJNAH-SY":{"name":{"en":"Kafr Sajnah","ar":"","fr":""},"code":"KAFR-SAJNAH-SY","countryCode":"SY"},"AL-BUWAYDAH-SY":{"name":{"en":"Al Buwaydah","ar":"","fr":""},"code":"AL-BUWAYDAH-SY","countryCode":"SY"},"HISH-SY":{"name":{"en":"Hish","ar":"","fr":""},"code":"HISH-SY","countryCode":"SY"},"AL-QARDAHAH-SY":{"name":{"en":"Al Qardahah","ar":"","fr":""},"code":"AL-QARDAHAH-SY","countryCode":"SY"},"ABU-HARDUB-SY":{"name":{"en":"Abu Hardub","ar":"","fr":""},"code":"ABU-HARDUB-SY","countryCode":"SY"},"AD-DARBASIYAH-SY":{"name":{"en":"Ad Darbasiyah","ar":"","fr":""},"code":"AD-DARBASIYAH-SY","countryCode":"SY"},"TAFTANAZ-SY":{"name":{"en":"Taftanaz","ar":"","fr":""},"code":"TAFTANAZ-SY","countryCode":"SY"},"RA'S-AL-MA`ARRAH-SY":{"name":{"en":"Ra's al Ma`arrah","ar":"","fr":""},"code":"RA'S-AL-MA`ARRAH-SY","countryCode":"SY"},"AL-QUNAYTIRAH-SY":{"name":{"en":"Al Qunaytirah","ar":"","fr":""},"code":"AL-QUNAYTIRAH-SY","countryCode":"SY"}}}